rpp/__init__.py
rpp/address.py
rpp/cli.py
rpp/i18n.py
rpp/resolver.py
rpp/visual.py
rpp/adapters/__init__.py
rpp/adapters/filesystem.py
rpp/adapters/memory.py
rpp_protocol-0.1.9.dist-info/METADATA
rpp_protocol-0.1.9.dist-info/WHEEL
rpp_protocol-0.1.9.dist-info/entry_points.txt
rpp_protocol-0.1.9.dist-info/licenses/LICENSE
rpp_protocol-0.1.9.dist-info/RECORD
