Metadata-Version: 2.4
Name: rpp-protocol
Version: 0.1.9
Summary: Rotational Packet Protocol - 28-bit semantic addressing for consent-aware systems
Project-URL: Homepage, https://github.com/anywave/rpp-spec
Project-URL: Documentation, https://github.com/anywave/rpp-spec
Project-URL: Repository, https://github.com/anywave/rpp-spec
Project-URL: Issues, https://github.com/anywave/rpp-spec/issues
Author: Alexander Liam Lennon
License-Expression: Apache-2.0
License-File: LICENSE
Keywords: consent,protocol,routing,semantic-addressing
Classifier: Development Status :: 4 - Beta
Classifier: Environment :: Console
Classifier: Intended Audience :: Developers
Classifier: License :: OSI Approved :: Apache Software License
Classifier: Operating System :: OS Independent
Classifier: Programming Language :: Python :: 3
Classifier: Programming Language :: Python :: 3.9
Classifier: Programming Language :: Python :: 3.10
Classifier: Programming Language :: Python :: 3.11
Classifier: Programming Language :: Python :: 3.12
Classifier: Programming Language :: Python :: 3.13
Classifier: Topic :: Software Development :: Libraries :: Python Modules
Classifier: Typing :: Typed
Requires-Python: >=3.9
Provides-Extra: dev
Requires-Dist: pytest-cov>=4.0; extra == 'dev'
Requires-Dist: pytest>=7.0; extra == 'dev'
